funsecret/snapshot/__init__.py
funsecret/snapshot/snapshot.py
funsecret_snapshot-1.4.56.dist-info/METADATA
funsecret_snapshot-1.4.56.dist-info/WHEEL
funsecret_snapshot-1.4.56.dist-info/top_level.txt
funsecret_snapshot-1.4.56.dist-info/RECORD
