Metadata-Version: 2.4
Name: funsecret-snapshot
Version: 1.4.56
Summary: funsecret
Author-email: 牛哥 <niuliangtao@qq.com>, farfarfun <farfarfun@qq.com>
Maintainer-email: 牛哥 <niuliangtao@qq.com>, farfarfun <farfarfun@qq.com>
Project-URL: Organization, https://github.com/farfarfun
Project-URL: Repository, https://github.com/farfarfun/funsecret
Project-URL: Releases, https://github.com/farfarfun/funsecret/releases
Requires-Python: >=3.8
Requires-Dist: funsecret
Requires-Dist: funtable>=1.0.8
